pyfoxhole/__init__.py
pyfoxhole/_version.py
pyfoxhole/api.py
pyfoxhole/models.py
pyfoxhole-0.0.7.dist-info/LICENSE
pyfoxhole-0.0.7.dist-info/METADATA
pyfoxhole-0.0.7.dist-info/WHEEL
pyfoxhole-0.0.7.dist-info/top_level.txt
pyfoxhole-0.0.7.dist-info/RECORD
